{"stats":{"stat.pickup.minecraft.log":16,"stat.flyOneCm":20837,"stat.walkOneCm":22370,"stat.jump":98,"stat.mineBlock.minecraft.leaves":7,"stat.playOneMinute":6071,"stat.leaveGame":2,"stat.sneakTime":19,"stat.damageTaken":113,"stat.crouchOneCm":162,"stat.timeSinceDeath":6071,"stat.sprintOneCm":18086,"stat.mineBlock.minecraft.log":16,"stat.talkedToVillager":1},"stats_source":{"stat.pickup.minecraft.log":16,"stat.flyOneCm":20837,"stat.walkOneCm":22370,"stat.jump":98,"stat.mineBlock.minecraft.leaves":7,"stat.playOneMinute":6071,"stat.leaveGame":2,"stat.sneakTime":19,"stat.damageTaken":113,"stat.crouchOneCm":162,"stat.timeSinceDeath":6071,"stat.sprintOneCm":18086,"stat.mineBlock.minecraft.log":16,"stat.talkedToVillager":1},"advancements":{"minecraft:recipes/building_blocks/oak_planks":{"criteria":{"has_log":"2020-07-28 20:43:39 +0800"},"done":true},"minecraft:adventure/adventuring_time":{"criteria":{"forest_hills":"2020-07-28 20:43:28 +0800","plains":"2020-07-28 11:06:30 +0800"},"done":false}},"data":{"seen":1595940390975,"time_start":1595905589156,"time_last":1595940390975,"time_lived":303.55,"playername":"未知","names":[{"name":"未知","detectedAt":1690126948703}],"uuid_short":"813d8b1d139132b49b7a2309c4efd2a6","lastUpdate":1703956819000,"uuid":"813d8b1d-1391-32b4-9b7a-2309c4efd2a6","banned":false}}